nubefact/__init__.py
nubefact/client.py
nubefact/helpers.py
nubefact/models.py
nubefact_python-0.3.2.dist-info/METADATA
nubefact_python-0.3.2.dist-info/WHEEL
nubefact_python-0.3.2.dist-info/licenses/LICENSE
nubefact_python-0.3.2.dist-info/RECORD
