Metadata-Version: 2.4
Name: nubefact-python
Version: 0.3.2
Summary: Python client library for the Nubefact API - Peruvian electronic invoicing system
Project-URL: Homepage, https://github.com/sumaerp/nubefact-python
Project-URL: Documentation, https://github.com/sumaerp/nubefact-python#readme
Author-email: Quanta Solutions <sumaerp@bequanta.com>
Maintainer-email: Quanta Solutions <sumaerp@bequanta.com>
License: MIT
License-File: LICENSE
Keywords: electronic,electronica,facturacion,invoicing,nubefact,peru,sunat
Classifier: Development Status :: 4 - Beta
Classifier: Framework :: Pydantic
Classifier: Intended Audience :: Developers
Classifier: License :: OSI Approved :: MIT License
Classifier: Operating System :: OS Independent
Classifier: Programming Language :: Python :: 3
Classifier: Programming Language :: Python :: 3.11
Classifier: Programming Language :: Python :: 3.12
Classifier: Programming Language :: Python :: 3.13
Classifier: Topic :: Office/Business :: Financial :: Accounting
Classifier: Topic :: Software Development :: Libraries :: Python Modules
Requires-Python: >=3.11
Requires-Dist: httpx>=0.24.0
Requires-Dist: pydantic>=2.0.0
Provides-Extra: dev
Requires-Dist: black>=23.0.0; extra == 'dev'
Requires-Dist: isort>=5.12.0; extra == 'dev'
Requires-Dist: mypy>=1.0.0; extra == 'dev'
Requires-Dist: pytest-asyncio>=0.21.0; extra == 'dev'
Requires-Dist: pytest>=7.0.0; extra == 'dev'
Requires-Dist: ruff>=0.1.0; extra == 'dev'
